[
    {
        "user": "U05GJ4J95TN",
        "type": "message",
        "ts": "1747312132.127149",
        "edited": {
            "user": "U05GJ4J95TN",
            "ts": "1747312149.000000"
        },
        "client_msg_id": "ec8ed07f-f122-43f5-a1f1-d6bfffae0024",
        "text": "We've just submitted a Credential request from a Mainnet validator, logged into the Utility app via a separate partyID. I understand you need the requesting partyID to approve this but can I just confirm that would be the operator (root) partyID for that validator and not the partyID that logged in to create the request?",
        "team": "T05FWTX7PMG",
        "user_team": "T05G287EAP4",
        "source_team": "T05G287EAP4",
        "user_profile": {
            "avatar_hash": "3b740afb2f83",
            "image_72": "https:\/\/avatars.slack-edge.com\/2023-07-11\/5558683763189_3b740afb2f83ba8aaac8_72.jpg",
            "first_name": "Matt",
            "real_name": "Matt Shilston",
            "display_name": "Matt S",
            "team": "T05G287EAP4",
            "name": "matthew.shilston",
            "is_restricted": false,
            "is_ultra_restricted": false
        },
        "thread_ts": "1747312132.127149",
        "reply_count": 2,
        "reply_users_count": 2,
        "latest_reply": "1747312669.969529",
        "reply_users": [
            "U012DRCTM61",
            "U05GJ4J95TN"
        ],
        "replies": [
            {
                "user": "U012DRCTM61",
                "ts": "1747312272.162319"
            },
            {
                "user": "U05GJ4J95TN",
                "ts": "1747312669.969529"
            }
        ],
        "is_locked": false,
        "subscribed": false,
        "blocks": [
            {
                "type": "rich_text",
                "block_id": "KljCk",
                "elements": [
                    {
                        "type": "rich_text_section",
                        "elements": [
                            {
                                "type": "text",
                                "text": "We've just submitted a Credential request from a Mainnet validator, logged into the Utility app via a separate partyID. I understand you need the requesting partyID to approve this but can I just confirm that would be the operator (root) partyID for that validator and not the partyID that logged in to create the request?"
                            }
                        ]
                    }
                ]
            }
        ],
        "language": {
            "locale": "en",
            "is_reliable": true
        }
    },
    {
        "user": "U012DRCTM61",
        "type": "message",
        "ts": "1747312272.162319",
        "edited": {
            "user": "U012DRCTM61",
            "ts": "1747312297.000000"
        },
        "client_msg_id": "979E4162-88E2-4050-8988-73F4025311FA",
        "text": "Pretty sure it’s the user logged in. We logged into the utility with the same as the default validator user for the wallet ui so ours is the same but I’ve sent credentials to different party ids than the validator id to people who logged into the utility under a separate user",
        "team": "T05FWTX7PMG",
        "user_team": "T0120EZF35M",
        "source_team": "T0120EZF35M",
        "user_profile": {
            "avatar_hash": "355d668ed46e",
            "image_72": "https:\/\/avatars.slack-edge.com\/2025-03-03\/8540513358466_355d668ed46e2141ccc2_72.png",
            "first_name": "Ben",
            "real_name": "Ben Latz",
            "display_name": "",
            "team": "T0120EZF35M",
            "name": "blatz",
            "is_restricted": false,
            "is_ultra_restricted": false
        },
        "thread_ts": "1747312132.127149",
        "parent_user_id": "U05GJ4J95TN",
        "blocks": [
            {
                "type": "rich_text",
                "block_id": "mR9dh",
                "elements": [
                    {
                        "type": "rich_text_section",
                        "elements": [
                            {
                                "type": "text",
                                "text": "Pretty sure it’s the user logged in. We logged into the utility with the same as the default validator user for the wallet ui "
                            },
                            {
                                "type": "text",
                                "text": "so ours is the same but"
                            },
                            {
                                "type": "text",
                                "text": " I’ve sent credentials to different party ids than the validator id to people who logged into the utility under a separate user"
                            }
                        ]
                    }
                ]
            }
        ],
        "language": {
            "locale": "en",
            "is_reliable": true
        }
    },
    {
        "user": "U05GJ4J95TN",
        "type": "message",
        "ts": "1747312669.969529",
        "client_msg_id": "c5b87b1a-5ef9-4983-a566-934e2fe007c4",
        "text": "OK thanks Ben, this is what we've done too.\n\nCan anyone see the request from the following then?\n\nauth0_007c67f69eb75222d72472300db6::12209379a423806e27ac0005e83cec9960e500bee21d40da48428469fe9b93f80849",
        "team": "T05FWTX7PMG",
        "user_team": "T05G287EAP4",
        "source_team": "T05G287EAP4",
        "user_profile": {
            "avatar_hash": "3b740afb2f83",
            "image_72": "https:\/\/avatars.slack-edge.com\/2023-07-11\/5558683763189_3b740afb2f83ba8aaac8_72.jpg",
            "first_name": "Matt",
            "real_name": "Matt Shilston",
            "display_name": "Matt S",
            "team": "T05G287EAP4",
            "name": "matthew.shilston",
            "is_restricted": false,
            "is_ultra_restricted": false
        },
        "thread_ts": "1747312132.127149",
        "parent_user_id": "U05GJ4J95TN",
        "blocks": [
            {
                "type": "rich_text",
                "block_id": "\/QUUP",
                "elements": [
                    {
                        "type": "rich_text_section",
                        "elements": [
                            {
                                "type": "text",
                                "text": "OK thanks Ben, this is what we've done too.\n\nCan anyone see the request from the following then?\n\nauth0_007c67f69eb75222d72472300db6::12209379a423806e27ac0005e83cec9960e500bee21d40da48428469fe9b93f80849"
                            }
                        ]
                    }
                ]
            }
        ],
        "language": {
            "locale": "en",
            "is_reliable": true
        }
    },
    {
        "user": "U05GJ4J95TN",
        "type": "message",
        "ts": "1747317430.939149",
        "client_msg_id": "5c507140-f3a0-4cf5-b3a8-13041b36996e",
        "text": "Please could I request approval for the credential request coming from:\n\nauth0_007c67f69eb75222d72472300db6::12209379a423806e27ac0005e83cec9960e500bee21d40da48428469fe9b93f80849",
        "team": "T05FWTX7PMG",
        "user_team": "T05G287EAP4",
        "source_team": "T05G287EAP4",
        "user_profile": {
            "avatar_hash": "3b740afb2f83",
            "image_72": "https:\/\/avatars.slack-edge.com\/2023-07-11\/5558683763189_3b740afb2f83ba8aaac8_72.jpg",
            "first_name": "Matt",
            "real_name": "Matt Shilston",
            "display_name": "Matt S",
            "team": "T05G287EAP4",
            "name": "matthew.shilston",
            "is_restricted": false,
            "is_ultra_restricted": false
        },
        "thread_ts": "1747317430.939149",
        "reply_count": 1,
        "reply_users_count": 1,
        "latest_reply": "1747317669.160739",
        "reply_users": [
            "U05GJ4J95TN"
        ],
        "replies": [
            {
                "user": "U05GJ4J95TN",
                "ts": "1747317669.160739"
            }
        ],
        "is_locked": false,
        "subscribed": false,
        "blocks": [
            {
                "type": "rich_text",
                "block_id": "Pix4j",
                "elements": [
                    {
                        "type": "rich_text_section",
                        "elements": [
                            {
                                "type": "text",
                                "text": "Please could I request approval for the credential request coming from:\n\nauth0_007c67f69eb75222d72472300db6::12209379a423806e27ac0005e83cec9960e500bee21d40da48428469fe9b93f80849"
                            }
                        ]
                    }
                ]
            }
        ],
        "language": {
            "locale": "en",
            "is_reliable": true
        }
    },
    {
        "user": "U05GJ4J95TN",
        "type": "message",
        "ts": "1747317669.160739",
        "client_msg_id": "98ba7e78-7f39-4d2b-819e-5a7254d4b2ae",
        "text": "many thanks!",
        "team": "T05FWTX7PMG",
        "user_team": "T05G287EAP4",
        "source_team": "T05G287EAP4",
        "user_profile": {
            "avatar_hash": "3b740afb2f83",
            "image_72": "https:\/\/avatars.slack-edge.com\/2023-07-11\/5558683763189_3b740afb2f83ba8aaac8_72.jpg",
            "first_name": "Matt",
            "real_name": "Matt Shilston",
            "display_name": "Matt S",
            "team": "T05G287EAP4",
            "name": "matthew.shilston",
            "is_restricted": false,
            "is_ultra_restricted": false
        },
        "thread_ts": "1747317430.939149",
        "parent_user_id": "U05GJ4J95TN",
        "blocks": [
            {
                "type": "rich_text",
                "block_id": "gBK01",
                "elements": [
                    {
                        "type": "rich_text_section",
                        "elements": [
                            {
                                "type": "text",
                                "text": "many thanks!"
                            }
                        ]
                    }
                ]
            }
        ]
    }
]