[
    {
        "subtype": "channel_join",
        "user": "U08JNLKMH60",
        "text": "<@U08JNLKMH60> has joined the channel",
        "type": "message",
        "ts": "1751967279.562119"
    },
    {
        "subtype": "channel_join",
        "user": "U091F8WHDC3",
        "text": "<@U091F8WHDC3> has joined the channel",
        "inviter": "U08JNLKMH60",
        "type": "message",
        "ts": "1751967286.599689"
    },
    {
        "subtype": "channel_join",
        "user": "U094E5JBLS3",
        "text": "<@U094E5JBLS3> has joined the channel",
        "type": "message",
        "ts": "1751989366.212099"
    },
    {
        "subtype": "bot_message",
        "text": "\nGood News! New customer for BitSafe Vault \n\nCompany Name: example\n\nName: example\n\nEmail: hello@acme.inc\n\nTelegram: example\n\nThey are interested in XBTO Trend\n\nSheet link:\n\n<https:\/\/docs.google.com\/spreadsheets\/d\/1dLYc1l73UGlFvf1tgYBRqqOnoeQtvd5QHptsSld1_O8>",
        "username": "BitSafe Vault Update",
        "type": "message",
        "ts": "1751989366.975379",
        "bot_id": "B094E5JBA3Z",
        "app_id": "A024R9PQM",
        "blocks": [
            {
                "type": "rich_text",
                "block_id": "wOv",
                "elements": [
                    {
                        "type": "rich_text_section",
                        "elements": [
                            {
                                "type": "text",
                                "text": "Good News! New customer for BitSafe Vault \n\nCompany Name: example\n\nName: example\n\nEmail: hello@acme.inc\n\nTelegram: example\n\nThey are interested in XBTO Trend\n\nSheet link:\n\n"
                            },
                            {
                                "type": "link",
                                "url": "https:\/\/docs.google.com\/spreadsheets\/d\/1dLYc1l73UGlFvf1tgYBRqqOnoeQtvd5QHptsSld1_O8"
                            }
                        ]
                    }
                ]
            }
        ]
    }
]